{
  "metas": [
    {
      "id": "tmdb:31688",
      "type": "series",
      "name": "Porno Verde",
      "ids": {
        "tmdb": 31688
      },
      "overview": "Una serie de cortometrajes inspirados en las asombrosas y a menudo extrañas prácticas sexuales de los insectos y otras criaturas.",
      "year": 2008,
      "poster": "https://image.tmdb.org/t/p/w342/3ORqPBuoCAHEB69wTSXuqbZ6uRK.jpg",
      "posterShape": "poster",
      "backdrop": "https://image.tmdb.org/t/p/original/oJ2aHeeB5ZmCZfH6jK9IaEeHHdC.jpg"
    }
  ]
}